dbt_cloud_client/__init__.py
dbt_cloud_client/api_client.py
dbt_cloud_client/configuration.py
dbt_cloud_client/rest.py
dbt_cloud_client/api/__init__.py
dbt_cloud_client/api/accounts_api.py
dbt_cloud_client/api/connections_api.py
dbt_cloud_client/api/credentials_api.py
dbt_cloud_client/api/environments_api.py
dbt_cloud_client/api/jobs_api.py
dbt_cloud_client/api/repositories_api.py
dbt_cloud_client/api/runs_api.py
dbt_cloud_client/models/__init__.py
dbt_cloud_client/models/account.py
dbt_cloud_client/models/account_response.py
dbt_cloud_client/models/accounts_response.py
dbt_cloud_client/models/bigquery_connection.py
dbt_cloud_client/models/bigquery_credential.py
dbt_cloud_client/models/body.py
dbt_cloud_client/models/body1.py
dbt_cloud_client/models/body2.py
dbt_cloud_client/models/body3.py
dbt_cloud_client/models/body4.py
dbt_cloud_client/models/connection.py
dbt_cloud_client/models/connection_response.py
dbt_cloud_client/models/connections_response.py
dbt_cloud_client/models/credentials_response.py
dbt_cloud_client/models/environment.py
dbt_cloud_client/models/environment_response.py
dbt_cloud_client/models/environments_response.py
dbt_cloud_client/models/error_response.py
dbt_cloud_client/models/job.py
dbt_cloud_client/models/job_response.py
dbt_cloud_client/models/job_schedule.py
dbt_cloud_client/models/job_schedule_date.py
dbt_cloud_client/models/job_schedule_time.py
dbt_cloud_client/models/job_settings.py
dbt_cloud_client/models/job_triggers.py
dbt_cloud_client/models/jobs_response.py
dbt_cloud_client/models/one_of_connection_response_data.py
dbt_cloud_client/models/one_ofbody.py
dbt_cloud_client/models/one_ofbody1.py
dbt_cloud_client/models/one_ofbody2.py
dbt_cloud_client/models/repositories_response.py
dbt_cloud_client/models/repository.py
dbt_cloud_client/models/repository_response.py
dbt_cloud_client/models/run.py
dbt_cloud_client/models/run_response.py
dbt_cloud_client/models/runs_response.py
dbt_cloud_client/models/status.py
dbt_cloud_client-0.0.1.dist-info/METADATA
dbt_cloud_client-0.0.1.dist-info/WHEEL
dbt_cloud_client-0.0.1.dist-info/top_level.txt
dbt_cloud_client-0.0.1.dist-info/RECORD
