Metadata-Version: 2.1
Name: dbt-cloud-client
Version: 0.0.1
Summary: dbt Cloud API v2
Home-page: UNKNOWN
Author: UNKNOWN
Author-email: alessandro@huq.io
License: UNKNOWN
Keywords: Swagger,dbt Cloud API v2
Platform: UNKNOWN
Requires-Dist: urllib3 (>=1.15)
Requires-Dist: six (>=1.10)
Requires-Dist: certifi
Requires-Dist: python-dateutil
